README.rst
setup.py
wedutil/__init__.py
wedutil.egg-info/PKG-INFO
wedutil.egg-info/SOURCES.txt
wedutil.egg-info/dependency_links.txt
wedutil.egg-info/top_level.txt