Metadata-Version: 1.1
Name: wedutil
Version: 0.22.1
Summary: Utilities for testing wed with Selenium.
Home-page: https://github.com/mangalam-research/wedutil
Author: Louis-Dominique Dubeau
Author-email: ldd@lddubeau.com
License: MPL 2.0
Keywords: wed,selenium,testing
Platform: UNKNOWN
Classifier: Programming Language :: Python :: 3 :: Only
Classifier: Development Status :: 4 - Beta
Classifier: Intended Audience :: Developers
Classifier: License :: OSI Approved :: Mozilla Public License 2.0 (MPL 2.0)
Classifier: Operating System :: POSIX
Classifier: Topic :: Software Development :: Testing
Classifier: Topic :: Software Development :: Quality Assurance
